llm_tester/__init__.py
llm_tester/__main__.py
llm_tester/cli_tool.py
llm_tester/conversation.py
llm_tester/misc.py
llm_tester/reporting.py
llm_tester/testing.py
llm_tester/validate.py
llm_tester-0.1.0.dist-info/METADATA
llm_tester-0.1.0.dist-info/WHEEL
llm_tester-0.1.0.dist-info/RECORD
