Metadata-Version: 2.1
Name: llm-tester
Version: 0.1.0
Summary: 
Author: Ezequiel Panzarasa
Author-email: ezequiel.panzarasa@qubika.com
Requires-Python: ==3.10.13
Classifier: Programming Language :: Python :: 3
Requires-Dist: click (>=8.1.7,<9.0.0)
Requires-Dist: langchain (==0.0.345)
Requires-Dist: openai (>=1.8.0,<2.0.0)
Requires-Dist: pandas (>=2.1.4,<3.0.0)
